lightquakevisualizer/__init__.py
lightquakevisualizer/generateColorBar.py
lightquakevisualizer/imageCombiner.py
lightquakevisualizer/lightQuakeVisualizer.py
lightquakevisualizer/test.py
lightquakevisualizer-0.3.7.dist-info/licenses/LICENSE
lightquakevisualizer-0.3.7.dist-info/METADATA
lightquakevisualizer-0.3.7.dist-info/WHEEL
lightquakevisualizer-0.3.7.dist-info/entry_points.txt
lightquakevisualizer-0.3.7.dist-info/top_level.txt
lightquakevisualizer-0.3.7.dist-info/RECORD
