Metadata-Version: 2.4
Name: lightquakevisualizer
Version: 0.3.7
Summary: A collection of scripts for visualizing output from earthquake simulation software
Author: Thomas Ulrich
License-Expression: MIT
Project-URL: Repository, https://github.com/Thomas-Ulrich/light-quake-visualizer.git
Keywords: pyvista,SeisSol
Classifier: Programming Language :: Python :: 3
Classifier: Operating System :: OS Independent
Requires-Python: >=3.10
License-File: LICENSE
Requires-Dist: cmasher
Requires-Dist: cmcrameri
Requires-Dist: matplotlib
Requires-Dist: numpy
Requires-Dist: pyvista
Requires-Dist: seissolxdmf>=0.1.3
Requires-Dist: vtk
Requires-Dist: Pillow
Dynamic: license-file
